MANIFEST.in
README.txt
setup.cfg
setup.py
asv_utils/__init__.py
asv_utils/common.py
asv_utils.egg-info/PKG-INFO
asv_utils.egg-info/SOURCES.txt
asv_utils.egg-info/dependency_links.txt
asv_utils.egg-info/not-zip-safe
asv_utils.egg-info/requires.txt
asv_utils.egg-info/top_level.txt
asv_utils/dj/__init__.py
asv_utils/dj/middleware.py