Metadata-Version: 1.0
Name: asv-utils
Version: dev-20120401-01
Summary: 
